{
    "0": [
        [
            [
                2,
                0
            ],
            -0.7933305466343268
        ],
        [
            [
                3,
                -2
            ],
            0.6859032294855909
        ]
    ],
    "1": [
        [
            [
                0,
                0
            ],
            0.8448046710634948
        ],
        [
            [
                2,
                0
            ],
            0.9563700135491651
        ],
        [
            [
                3,
                0
            ],
            -0.8394882513220523
        ],
        [
            [
                4,
                0
            ],
            0.9695587695260912
        ]
    ],
    "2": [],
    "3": [
        [
            [
                2,
                -1
            ],
            -0.7802546895918157
        ]
    ],
    "4": [
        [
            [
                0,
                -2
            ],
            -0.7847467286299492
        ],
        [
            [
                2,
                0
            ],
            0.5988346633990485
        ],
        [
            [
                3,
                -1
            ],
            -0.8981753873124931
        ]
    ]
}