{
    "0": [
        [
            [
                1,
                -2
            ],
            0.9751901911589043
        ],
        [
            [
                2,
                -1
            ],
            -0.5065525758932048
        ],
        [
            [
                3,
                0
            ],
            0.5217781031723465
        ],
        [
            [
                5,
                -1
            ],
            -0.9919474031165968
        ],
        [
            [
                9,
                0
            ],
            0.841394562997709
        ]
    ],
    "1": [
        [
            [
                3,
                -2
            ],
            0.9399540550420245
        ],
        [
            [
                5,
                0
            ],
            0.9260562323286523
        ],
        [
            [
                9,
                -2
            ],
            0.782409565885983
        ]
    ],
    "2": [
        [
            [
                1,
                -2
            ],
            -0.5444597617917295
        ],
        [
            [
                3,
                -1
            ],
            0.5098532388773476
        ],
        [
            [
                5,
                0
            ],
            -0.9168523715052341
        ],
        [
            [
                9,
                -1
            ],
            -0.8374622557783025
        ]
    ],
    "3": [
        [
            [
                9,
                0
            ],
            -0.6291992748739264
        ]
    ],
    "4": [
        [
            [
                0,
                0
            ],
            0.9260294024562671
        ],
        [
            [
                1,
                -1
            ],
            0.8321316570700086
        ],
        [
            [
                2,
                -2
            ],
            0.8972986980025144
        ],
        [
            [
                3,
                -2
            ],
            0.886177790992994
        ],
        [
            [
                5,
                -2
            ],
            -0.5747926539740515
        ],
        [
            [
                7,
                -1
            ],
            -0.7346202235585436
        ],
        [
            [
                8,
                -1
            ],
            0.800046423337587
        ],
        [
            [
                9,
                -1
            ],
            -0.9619743873345737
        ]
    ],
    "5": [],
    "6": [
        [
            [
                0,
                -1
            ],
            0.9417378383258905
        ],
        [
            [
                1,
                -2
            ],
            0.794910827211038
        ],
        [
            [
                2,
                -2
            ],
            0.7336770451071375
        ],
        [
            [
                3,
                -1
            ],
            -0.6702565572808045
        ],
        [
            [
                4,
                -1
            ],
            -0.614034306837655
        ],
        [
            [
                5,
                -1
            ],
            0.7574868040451379
        ],
        [
            [
                7,
                0
            ],
            0.8347260718843814
        ],
        [
            [
                8,
                -1
            ],
            -0.792554810759239
        ],
        [
            [
                9,
                -1
            ],
            -0.9371384442502999
        ]
    ],
    "7": [
        [
            [
                3,
                -2
            ],
            -0.6175124972804342
        ],
        [
            [
                5,
                0
            ],
            -0.8187904985434102
        ],
        [
            [
                9,
                0
            ],
            -0.6119760620214796
        ]
    ],
    "8": [
        [
            [
                0,
                -1
            ],
            0.6508880899842511
        ],
        [
            [
                1,
                -1
            ],
            0.9107287984190024
        ],
        [
            [
                2,
                0
            ],
            -0.8203534393745509
        ],
        [
            [
                3,
                -1
            ],
            -0.7588852052561649
        ],
        [
            [
                5,
                -1
            ],
            -0.8258899445161425
        ],
        [
            [
                7,
                -1
            ],
            0.5749143438266
        ],
        [
            [
                9,
                -2
            ],
            0.5480134164621626
        ]
    ],
    "9": [
        [
            [
                5,
                -2
            ],
            0.74698953688689
        ]
    ]
}