{
    "0": [
        [
            [
                1,
                -1
            ],
            0.826926210343207
        ],
        [
            [
                3,
                0
            ],
            0.5691834468759346
        ],
        [
            [
                4,
                0
            ],
            -0.7834696715244621
        ],
        [
            [
                7,
                -1
            ],
            0.9283174428779808
        ],
        [
            [
                11,
                0
            ],
            -0.9373748760012662
        ],
        [
            [
                15,
                -4
            ],
            -0.6351359172141654
        ],
        [
            [
                16,
                -4
            ],
            0.62736367214576
        ],
        [
            [
                18,
                -3
            ],
            0.8277610990726445
        ],
        [
            [
                19,
                -3
            ],
            0.774488085372044
        ]
    ],
    "1": [
        [
            [
                8,
                -3
            ],
            0.6154852486410765
        ],
        [
            [
                11,
                -3
            ],
            0.6999247000221729
        ],
        [
            [
                15,
                -3
            ],
            0.6462238662313955
        ],
        [
            [
                16,
                -1
            ],
            0.7103286052653652
        ],
        [
            [
                19,
                -4
            ],
            0.5198632602268722
        ]
    ],
    "2": [
        [
            [
                1,
                -4
            ],
            -0.6813791800977721
        ],
        [
            [
                3,
                -4
            ],
            0.9281891544617935
        ],
        [
            [
                4,
                -1
            ],
            0.9803940074636118
        ],
        [
            [
                5,
                0
            ],
            -0.9797256783026628
        ],
        [
            [
                6,
                0
            ],
            -0.8707418386673496
        ],
        [
            [
                7,
                -1
            ],
            -0.7680620413399827
        ],
        [
            [
                8,
                -3
            ],
            0.973643005099849
        ],
        [
            [
                11,
                -1
            ],
            0.5947275684130552
        ],
        [
            [
                15,
                -4
            ],
            0.8276669684278191
        ],
        [
            [
                16,
                -4
            ],
            -0.7939393164200302
        ]
    ],
    "3": [
        [
            [
                8,
                -4
            ],
            0.9696857603153791
        ],
        [
            [
                11,
                -2
            ],
            -0.6638041121531993
        ]
    ],
    "4": [
        [
            [
                1,
                -1
            ],
            -0.8941242396985802
        ],
        [
            [
                3,
                0
            ],
            -0.5174447158576979
        ],
        [
            [
                5,
                -3
            ],
            -0.8970616391008915
        ],
        [
            [
                8,
                -2
            ],
            -0.8216036248031227
        ],
        [
            [
                11,
                -1
            ],
            -0.9004058580001273
        ],
        [
            [
                15,
                0
            ],
            0.9590154512044513
        ],
        [
            [
                16,
                -2
            ],
            0.5643438010961555
        ],
        [
            [
                19,
                -3
            ],
            -0.6364887316709651
        ]
    ],
    "5": [
        [
            [
                3,
                -2
            ],
            0.5842827667744506
        ],
        [
            [
                8,
                -3
            ],
            -0.5536951884160752
        ],
        [
            [
                11,
                -4
            ],
            -0.7974673373668169
        ],
        [
            [
                15,
                -4
            ],
            0.5581351015798159
        ],
        [
            [
                16,
                -4
            ],
            0.6644925022239899
        ]
    ],
    "6": [
        [
            [
                3,
                0
            ],
            0.7124739251827797
        ],
        [
            [
                4,
                -3
            ],
            0.8193384699468833
        ],
        [
            [
                5,
                -2
            ],
            -0.7738350800487857
        ],
        [
            [
                7,
                -1
            ],
            -0.5386075604855662
        ],
        [
            [
                8,
                -4
            ],
            0.848467498638009
        ],
        [
            [
                15,
                -4
            ],
            -0.5172425649571131
        ],
        [
            [
                16,
                -4
            ],
            -0.632283124613064
        ],
        [
            [
                18,
                0
            ],
            -0.9364525483518874
        ]
    ],
    "7": [
        [
            [
                1,
                -2
            ],
            -0.7072070282718966
        ],
        [
            [
                3,
                -4
            ],
            -0.8007401792207375
        ],
        [
            [
                4,
                -4
            ],
            -0.7601079711980422
        ],
        [
            [
                5,
                -1
            ],
            -0.9649741543423628
        ],
        [
            [
                8,
                -3
            ],
            0.6942671406777643
        ],
        [
            [
                11,
                -3
            ],
            -0.6436892585398448
        ],
        [
            [
                16,
                -1
            ],
            0.5266222846940863
        ],
        [
            [
                18,
                -3
            ],
            0.9683039970848552
        ],
        [
            [
                19,
                -4
            ],
            -0.9430604439415844
        ]
    ],
    "8": [],
    "9": [
        [
            [
                0,
                -3
            ],
            -0.8789225390516044
        ],
        [
            [
                1,
                -4
            ],
            0.9907190725711849
        ],
        [
            [
                2,
                0
            ],
            -0.5885267480280332
        ],
        [
            [
                4,
                -2
            ],
            0.6743941398328641
        ],
        [
            [
                5,
                -3
            ],
            0.573419058255485
        ],
        [
            [
                6,
                -3
            ],
            0.8800702718130724
        ],
        [
            [
                7,
                -3
            ],
            -0.9025099254508119
        ],
        [
            [
                11,
                -2
            ],
            0.5730894689388023
        ],
        [
            [
                12,
                -3
            ],
            0.8848797042751396
        ],
        [
            [
                14,
                -2
            ],
            -0.7389283490273977
        ],
        [
            [
                15,
                -1
            ],
            0.9694515986752317
        ],
        [
            [
                16,
                0
            ],
            0.571003318894132
        ],
        [
            [
                17,
                -4
            ],
            0.780871204655331
        ],
        [
            [
                18,
                -4
            ],
            -0.8196906116449232
        ],
        [
            [
                19,
                -1
            ],
            0.5944575060672235
        ]
    ],
    "10": [
        [
            [
                0,
                0
            ],
            -0.6198671726725811
        ],
        [
            [
                1,
                -1
            ],
            0.6874617662449399
        ],
        [
            [
                2,
                -1
            ],
            -0.8484589060492992
        ],
        [
            [
                3,
                0
            ],
            0.9422376134983077
        ],
        [
            [
                4,
                0
            ],
            -0.948963020784747
        ],
        [
            [
                5,
                -2
            ],
            0.9872518602555331
        ],
        [
            [
                6,
                -2
            ],
            0.8169357299589972
        ],
        [
            [
                9,
                -2
            ],
            -0.5072344348220004
        ],
        [
            [
                11,
                -1
            ],
            0.8313959428033426
        ],
        [
            [
                12,
                -3
            ],
            -0.8300765969183796
        ],
        [
            [
                13,
                -4
            ],
            -0.5706036078840652
        ],
        [
            [
                15,
                -2
            ],
            0.832045020808543
        ],
        [
            [
                17,
                -3
            ],
            0.6375279923390668
        ],
        [
            [
                18,
                -4
            ],
            0.6044242252949665
        ],
        [
            [
                19,
                -3
            ],
            -0.8130924931374686
        ]
    ],
    "11": [],
    "12": [
        [
            [
                0,
                -2
            ],
            -0.7366864375789794
        ],
        [
            [
                2,
                0
            ],
            0.9609547435439227
        ],
        [
            [
                4,
                -4
            ],
            -0.7302813421718828
        ],
        [
            [
                5,
                -4
            ],
            0.5716266943228328
        ],
        [
            [
                8,
                -4
            ],
            -0.9487594735982833
        ],
        [
            [
                11,
                0
            ],
            -0.709448892006364
        ],
        [
            [
                15,
                -2
            ],
            -0.7158081933955273
        ],
        [
            [
                17,
                -1
            ],
            -0.9347308536390975
        ],
        [
            [
                19,
                -1
            ],
            0.9287243444177505
        ]
    ],
    "13": [
        [
            [
                1,
                -3
            ],
            0.8210913997752615
        ],
        [
            [
                2,
                -2
            ],
            0.74235105550577
        ],
        [
            [
                3,
                -1
            ],
            -0.6704074759993486
        ],
        [
            [
                4,
                0
            ],
            -0.6249575990186638
        ],
        [
            [
                5,
                -1
            ],
            0.9557765524163829
        ],
        [
            [
                7,
                -4
            ],
            0.5152982023763835
        ],
        [
            [
                11,
                -2
            ],
            0.6736105514751782
        ],
        [
            [
                12,
                -4
            ],
            -0.7049673558463206
        ],
        [
            [
                14,
                0
            ],
            -0.530201739687034
        ],
        [
            [
                15,
                -4
            ],
            0.5416553399571524
        ],
        [
            [
                16,
                -2
            ],
            -0.6482464265885469
        ],
        [
            [
                17,
                0
            ],
            -0.8123041959120754
        ],
        [
            [
                19,
                -4
            ],
            -0.9443920290360854
        ]
    ],
    "14": [
        [
            [
                0,
                -2
            ],
            -0.6483889867806494
        ],
        [
            [
                1,
                0
            ],
            -0.8984916301581964
        ],
        [
            [
                2,
                0
            ],
            0.8419854237593987
        ],
        [
            [
                3,
                0
            ],
            0.9532992998773813
        ],
        [
            [
                5,
                -1
            ],
            -0.9196030385866463
        ],
        [
            [
                6,
                -4
            ],
            0.7307087844274404
        ],
        [
            [
                7,
                -1
            ],
            -0.6190060142517158
        ],
        [
            [
                8,
                -3
            ],
            -0.6791420097676066
        ],
        [
            [
                11,
                0
            ],
            -0.6521699298777038
        ],
        [
            [
                12,
                -1
            ],
            -0.5801544356005757
        ],
        [
            [
                16,
                -4
            ],
            0.6000618823249732
        ],
        [
            [
                17,
                0
            ],
            -0.823148125653798
        ],
        [
            [
                18,
                -4
            ],
            0.9725713298722216
        ],
        [
            [
                19,
                -2
            ],
            -0.5296035141030357
        ]
    ],
    "15": [
        [
            [
                3,
                -2
            ],
            0.7109565831196243
        ],
        [
            [
                8,
                -3
            ],
            0.8654797667441028
        ],
        [
            [
                16,
                -4
            ],
            0.8903199660471682
        ]
    ],
    "16": [
        [
            [
                11,
                -3
            ],
            -0.9209492757329549
        ]
    ],
    "17": [
        [
            [
                0,
                0
            ],
            0.8530139817086033
        ],
        [
            [
                1,
                0
            ],
            -0.7499229998247303
        ],
        [
            [
                2,
                -3
            ],
            0.8440981496549558
        ],
        [
            [
                3,
                -2
            ],
            0.7017255085279244
        ],
        [
            [
                4,
                -3
            ],
            0.8136940950215558
        ],
        [
            [
                5,
                -3
            ],
            0.954206887293177
        ],
        [
            [
                6,
                -1
            ],
            -0.6548120883412456
        ],
        [
            [
                7,
                0
            ],
            -0.7730018109212584
        ],
        [
            [
                8,
                -2
            ],
            -0.9151920025506268
        ],
        [
            [
                11,
                -3
            ],
            0.7974787541579186
        ],
        [
            [
                18,
                -1
            ],
            0.5310593239499893
        ],
        [
            [
                19,
                -3
            ],
            -0.828169727155281
        ]
    ],
    "18": [
        [
            [
                1,
                -4
            ],
            0.9250782027462228
        ],
        [
            [
                3,
                -4
            ],
            0.7899430958791651
        ],
        [
            [
                8,
                -1
            ],
            -0.9238841722842888
        ]
    ],
    "19": [
        [
            [
                3,
                -4
            ],
            0.6351859007063072
        ],
        [
            [
                5,
                -2
            ],
            0.6262017796770949
        ],
        [
            [
                8,
                -2
            ],
            0.5309172185933095
        ],
        [
            [
                11,
                0
            ],
            -0.8269261257952287
        ],
        [
            [
                15,
                0
            ],
            0.7893084338988878
        ]
    ]
}