{
    "0": [
        [
            [
                6,
                -4
            ],
            -0.7231616403247247
        ],
        [
            [
                7,
                -3
            ],
            0.8157381610324319
        ],
        [
            [
                9,
                -1
            ],
            0.6028595899775275
        ],
        [
            [
                11,
                -1
            ],
            0.8713583634001392
        ],
        [
            [
                16,
                -1
            ],
            -0.9706627588285357
        ],
        [
            [
                17,
                0
            ],
            0.6829529445762255
        ],
        [
            [
                18,
                -3
            ],
            -0.7158641507795467
        ]
    ],
    "1": [
        [
            [
                0,
                -2
            ],
            -0.6783011777097527
        ],
        [
            [
                5,
                0
            ],
            0.7040450897095505
        ],
        [
            [
                9,
                0
            ],
            -0.970578464553083
        ],
        [
            [
                10,
                -1
            ],
            0.8842273967726969
        ],
        [
            [
                11,
                -2
            ],
            0.9216056178050243
        ],
        [
            [
                12,
                -2
            ],
            0.944678720820025
        ],
        [
            [
                15,
                -2
            ],
            0.5928195835563401
        ],
        [
            [
                16,
                -2
            ],
            -0.9938202371285256
        ],
        [
            [
                17,
                -1
            ],
            0.5925564142530664
        ],
        [
            [
                18,
                -1
            ],
            0.6993253355154209
        ]
    ],
    "2": [
        [
            [
                0,
                -3
            ],
            0.7620747473946283
        ],
        [
            [
                3,
                -4
            ],
            0.58618486135095
        ],
        [
            [
                4,
                0
            ],
            0.8861490800414555
        ],
        [
            [
                5,
                -1
            ],
            -0.7010892535788542
        ],
        [
            [
                6,
                0
            ],
            -0.8769645646278845
        ],
        [
            [
                7,
                -3
            ],
            -0.5572710197635247
        ],
        [
            [
                8,
                -2
            ],
            -0.6615977653902306
        ],
        [
            [
                9,
                -3
            ],
            -0.8163398836999302
        ],
        [
            [
                10,
                -1
            ],
            -0.7049359022503752
        ],
        [
            [
                11,
                -1
            ],
            -0.6759008099206605
        ],
        [
            [
                12,
                -3
            ],
            -0.7234048636985303
        ],
        [
            [
                13,
                -2
            ],
            -0.5451775599098074
        ],
        [
            [
                14,
                -1
            ],
            0.6704101769544092
        ],
        [
            [
                16,
                -2
            ],
            0.9600279774755431
        ],
        [
            [
                17,
                -3
            ],
            -0.8889517937746074
        ],
        [
            [
                18,
                -4
            ],
            -0.6618476987130077
        ],
        [
            [
                19,
                -4
            ],
            -0.9617602213766572
        ]
    ],
    "3": [
        [
            [
                0,
                -3
            ],
            0.729864519464362
        ],
        [
            [
                1,
                -1
            ],
            -0.5989260334412612
        ],
        [
            [
                5,
                -1
            ],
            0.5951694151493977
        ],
        [
            [
                6,
                -4
            ],
            -0.8833695677956657
        ],
        [
            [
                7,
                0
            ],
            0.5860189945693475
        ],
        [
            [
                9,
                0
            ],
            -0.9660425246407328
        ],
        [
            [
                10,
                -1
            ],
            0.8807899048650036
        ],
        [
            [
                11,
                0
            ],
            0.8023852770904025
        ],
        [
            [
                12,
                0
            ],
            0.5851073272846117
        ],
        [
            [
                14,
                -3
            ],
            -0.6238090314387292
        ],
        [
            [
                15,
                -4
            ],
            -0.572061240498978
        ],
        [
            [
                16,
                -4
            ],
            0.841756776614554
        ],
        [
            [
                17,
                0
            ],
            -0.6173927395645888
        ],
        [
            [
                18,
                -4
            ],
            0.7665032613470502
        ],
        [
            [
                19,
                -3
            ],
            0.8437574210818346
        ]
    ],
    "4": [
        [
            [
                1,
                -1
            ],
            -0.5075679998026355
        ],
        [
            [
                6,
                -4
            ],
            -0.6067470341861008
        ],
        [
            [
                7,
                -4
            ],
            -0.7866811713900365
        ],
        [
            [
                10,
                -4
            ],
            -0.6457506712164255
        ],
        [
            [
                11,
                -2
            ],
            0.8675249703905747
        ],
        [
            [
                12,
                -4
            ],
            0.7079876908692939
        ],
        [
            [
                14,
                -4
            ],
            -0.5310948110606619
        ],
        [
            [
                15,
                -1
            ],
            -0.7166483323063806
        ],
        [
            [
                16,
                -2
            ],
            0.6029512949706668
        ],
        [
            [
                17,
                -2
            ],
            -0.8006334335355692
        ],
        [
            [
                18,
                -3
            ],
            -0.6220449445221463
        ],
        [
            [
                19,
                -4
            ],
            0.6169851921424905
        ]
    ],
    "5": [
        [
            [
                0,
                0
            ],
            0.8603961967857323
        ],
        [
            [
                6,
                -2
            ],
            -0.8041969794422104
        ],
        [
            [
                7,
                -1
            ],
            -0.8316475757038075
        ],
        [
            [
                9,
                -1
            ],
            -0.9373873425949775
        ],
        [
            [
                10,
                -4
            ],
            -0.938388955355233
        ],
        [
            [
                11,
                -3
            ],
            -0.9872507822767153
        ],
        [
            [
                12,
                -3
            ],
            -0.8280606403039414
        ],
        [
            [
                14,
                -3
            ],
            -0.6253808053731453
        ],
        [
            [
                15,
                -1
            ],
            0.8927561317121877
        ],
        [
            [
                16,
                0
            ],
            0.9217827784739439
        ],
        [
            [
                18,
                -2
            ],
            -0.8798154819042763
        ],
        [
            [
                19,
                0
            ],
            0.6945611377998082
        ]
    ],
    "6": [
        [
            [
                11,
                -4
            ],
            -0.5815456208602126
        ]
    ],
    "7": [
        [
            [
                6,
                -2
            ],
            -0.520992144773026
        ],
        [
            [
                9,
                -2
            ],
            0.94347635929361
        ],
        [
            [
                11,
                -4
            ],
            0.6482850090001016
        ],
        [
            [
                17,
                -1
            ],
            -0.6574902908466622
        ],
        [
            [
                18,
                -3
            ],
            -0.6342436914144636
        ]
    ],
    "8": [
        [
            [
                0,
                -3
            ],
            -0.9448894692406005
        ],
        [
            [
                1,
                -1
            ],
            0.881795988970614
        ],
        [
            [
                3,
                -3
            ],
            -0.913495538448486
        ],
        [
            [
                4,
                0
            ],
            0.7909509596399545
        ],
        [
            [
                5,
                -3
            ],
            -0.5394194603202151
        ],
        [
            [
                6,
                0
            ],
            -0.9947350795366485
        ],
        [
            [
                7,
                -3
            ],
            0.7896056913231352
        ],
        [
            [
                9,
                -4
            ],
            -0.798561107076925
        ],
        [
            [
                10,
                -3
            ],
            -0.6323272454691699
        ],
        [
            [
                11,
                -2
            ],
            -0.8973745017782621
        ],
        [
            [
                12,
                0
            ],
            -0.9961480676456738
        ],
        [
            [
                13,
                0
            ],
            -0.8215028812186354
        ],
        [
            [
                14,
                -2
            ],
            -0.6403117968441208
        ],
        [
            [
                15,
                -1
            ],
            -0.9293497552024677
        ],
        [
            [
                16,
                -2
            ],
            0.685670625889986
        ],
        [
            [
                17,
                -2
            ],
            0.566237470007444
        ],
        [
            [
                18,
                -3
            ],
            -0.7272284222207666
        ],
        [
            [
                19,
                -1
            ],
            0.6797872960006426
        ]
    ],
    "9": [
        [
            [
                11,
                -3
            ],
            -0.8858675202550779
        ],
        [
            [
                16,
                -2
            ],
            0.6571796945501822
        ],
        [
            [
                17,
                0
            ],
            0.6664416409878908
        ],
        [
            [
                18,
                0
            ],
            -0.5299714352565806
        ]
    ],
    "10": [
        [
            [
                0,
                -2
            ],
            0.5047959000739024
        ],
        [
            [
                6,
                -4
            ],
            -0.6884077793620205
        ],
        [
            [
                7,
                -4
            ],
            -0.6462232089960238
        ],
        [
            [
                9,
                -3
            ],
            -0.8093072337675038
        ],
        [
            [
                11,
                -4
            ],
            -0.5105520695572953
        ],
        [
            [
                14,
                -1
            ],
            -0.8625948828098536
        ],
        [
            [
                16,
                -3
            ],
            0.6929468653320849
        ],
        [
            [
                17,
                -1
            ],
            -0.5990219544080566
        ],
        [
            [
                18,
                0
            ],
            -0.7742699096257257
        ]
    ],
    "11": [],
    "12": [
        [
            [
                0,
                -3
            ],
            0.5365812958715662
        ],
        [
            [
                6,
                -3
            ],
            -0.6387004794942649
        ],
        [
            [
                7,
                -1
            ],
            -0.8377248000726667
        ],
        [
            [
                9,
                -4
            ],
            -0.792393546668759
        ],
        [
            [
                10,
                -1
            ],
            0.8857743641104947
        ],
        [
            [
                14,
                -1
            ],
            0.9750871298140908
        ],
        [
            [
                15,
                -4
            ],
            -0.9590104054638939
        ],
        [
            [
                16,
                -1
            ],
            -0.9924821086919002
        ],
        [
            [
                17,
                -2
            ],
            0.7319445351894911
        ],
        [
            [
                18,
                -3
            ],
            -0.8752459241936323
        ],
        [
            [
                19,
                -4
            ],
            -0.5643073228428896
        ]
    ],
    "13": [
        [
            [
                0,
                -3
            ],
            0.8096105921429568
        ],
        [
            [
                1,
                0
            ],
            0.7434506120301485
        ],
        [
            [
                3,
                -2
            ],
            0.9558781098405515
        ],
        [
            [
                4,
                -1
            ],
            0.9697720567771959
        ],
        [
            [
                5,
                -3
            ],
            0.7137238828469794
        ],
        [
            [
                6,
                -3
            ],
            0.9000460947167838
        ],
        [
            [
                7,
                -1
            ],
            0.8713941861719728
        ],
        [
            [
                9,
                -1
            ],
            0.8448356225858213
        ],
        [
            [
                10,
                -3
            ],
            -0.6991197868489158
        ],
        [
            [
                12,
                -4
            ],
            0.584711051467252
        ],
        [
            [
                14,
                -1
            ],
            0.9085876399386081
        ],
        [
            [
                16,
                -3
            ],
            0.984652560986636
        ],
        [
            [
                17,
                -1
            ],
            0.6204335236051273
        ],
        [
            [
                18,
                0
            ],
            -0.8823564062088081
        ]
    ],
    "14": [
        [
            [
                0,
                -3
            ],
            0.5428326752269965
        ],
        [
            [
                6,
                -3
            ],
            -0.9434407380920269
        ],
        [
            [
                9,
                -1
            ],
            0.9737060290778015
        ],
        [
            [
                11,
                -1
            ],
            -0.8069827514750632
        ],
        [
            [
                17,
                -4
            ],
            0.5837635339964375
        ]
    ],
    "15": [
        [
            [
                7,
                0
            ],
            -0.8735620457541484
        ],
        [
            [
                9,
                -2
            ],
            -0.8493094604146505
        ],
        [
            [
                10,
                -4
            ],
            0.5765557030434393
        ],
        [
            [
                14,
                -3
            ],
            0.916991773506373
        ],
        [
            [
                16,
                -2
            ],
            -0.6785313392501975
        ],
        [
            [
                17,
                -4
            ],
            -0.543159458354707
        ],
        [
            [
                18,
                -4
            ],
            -0.6343097748259348
        ],
        [
            [
                19,
                -1
            ],
            -0.8597051266286212
        ]
    ],
    "16": [
        [
            [
                11,
                0
            ],
            -0.653171446060737
        ]
    ],
    "17": [
        [
            [
                6,
                -4
            ],
            -0.8040516455147779
        ],
        [
            [
                11,
                -2
            ],
            0.5259756193193845
        ],
        [
            [
                18,
                -4
            ],
            -0.6462549926593366
        ]
    ],
    "18": [
        [
            [
                11,
                -2
            ],
            -0.6907156688071285
        ],
        [
            [
                16,
                -4
            ],
            0.8163671474202043
        ]
    ],
    "19": [
        [
            [
                0,
                -4
            ],
            0.8067770797417768
        ],
        [
            [
                6,
                -3
            ],
            0.8451666031163395
        ],
        [
            [
                7,
                0
            ],
            -0.5575277042569203
        ],
        [
            [
                9,
                -2
            ],
            0.8206049613416121
        ],
        [
            [
                10,
                -4
            ],
            -0.6012824735670238
        ],
        [
            [
                11,
                -1
            ],
            0.7102987160330787
        ],
        [
            [
                14,
                -1
            ],
            0.5598756752088229
        ],
        [
            [
                16,
                -2
            ],
            -0.9801112174042452
        ],
        [
            [
                17,
                0
            ],
            -0.6174833541572977
        ],
        [
            [
                18,
                -1
            ],
            -0.9638017922805285
        ]
    ]
}